jglr/__init__.py
jglr/main.py
jglr/parserobj.py
jglr/validation.py
jglr-0.2.1.dist-info/METADATA
jglr-0.2.1.dist-info/WHEEL
jglr-0.2.1.dist-info/entry_points.txt
jglr-0.2.1.dist-info/RECORD
