Metadata-Version: 2.4
Name: jglr
Version: 0.2.1
Summary: Add your description here
Author-email: Sai <ysaijagadeeshuh@gmail.com>
Requires-Python: >=3.10
Requires-Dist: datetime>=5.5
Requires-Dist: hatch>=1.14.0
Requires-Dist: pyautogui>=0.9.54
Requires-Dist: twine>=6.0.1
